pyreglin/__init__.py
pyreglin/dataset/__init__.py
pyreglin/dataset/load_data.py
pyreglin/graphics/__init__.py
pyreglin/graphics/gginfluence.py
pyreglin/graphics/ggresiduals.py
pyreglin/simdata/__init__.py
pyreglin/simdata/rlm.py
pyreglin/statistics/__init__.py
pyreglin/statistics/press.py
pyreglin/statistics/r2.py
pyreglin/statistics/residuals_test.py
pyreglin/tab_anova/__init__.py
pyreglin/tab_anova/tab_anova.py
pyreglin-1.0.0.dist-info/licenses/LICENSE
pyreglin-1.0.0.dist-info/METADATA
pyreglin-1.0.0.dist-info/WHEEL
pyreglin-1.0.0.dist-info/top_level.txt
pyreglin-1.0.0.dist-info/RECORD
